dlint/__init__.py
dlint/extension.py
dlint/multi.py
dlint/namespace.py
dlint/tree.py
dlint/util.py
dlint/linters/__init__.py
dlint/linters/bad_commands_use.py
dlint/linters/bad_compile_use.py
dlint/linters/bad_cryptography_module_attribute_use.py
dlint/linters/bad_defusedxml_use.py
dlint/linters/bad_dl_use.py
dlint/linters/bad_duo_client_use.py
dlint/linters/bad_eval_use.py
dlint/linters/bad_exec_use.py
dlint/linters/bad_gl_use.py
dlint/linters/bad_hashlib_use.py
dlint/linters/bad_input_use.py
dlint/linters/bad_itsdangerous_kwarg_use.py
dlint/linters/bad_marshal_use.py
dlint/linters/bad_onelogin_kwarg_use.py
dlint/linters/bad_onelogin_module_attribute_use.py
dlint/linters/bad_os_use.py
dlint/linters/bad_pickle_use.py
dlint/linters/bad_popen2_use.py
dlint/linters/bad_pycrypto_use.py
dlint/linters/bad_random_generator_use.py
dlint/linters/bad_re_catastrophic_use.py
dlint/linters/bad_requests_use.py
dlint/linters/bad_shelve_use.py
dlint/linters/bad_ssl_module_attribute_use.py
dlint/linters/bad_subprocess_use.py
dlint/linters/bad_sys_use.py
dlint/linters/bad_tarfile_use.py
dlint/linters/bad_tempfile_use.py
dlint/linters/bad_urllib3_kwarg_use.py
dlint/linters/bad_urllib3_module_attribute_use.py
dlint/linters/bad_xml_use.py
dlint/linters/bad_xmlrpc_use.py
dlint/linters/bad_xmlsec_module_attribute_use.py
dlint/linters/bad_yaml_use.py
dlint/linters/bad_zipfile_use.py
dlint/linters/base.py
dlint/linters/helpers/__init__.py
dlint/linters/helpers/bad_builtin_use.py
dlint/linters/helpers/bad_kwarg_use.py
dlint/linters/helpers/bad_module_attribute_use.py
dlint/linters/helpers/bad_module_use.py
dlint/linters/helpers/bad_name_attribute_use.py
dlint/linters/twisted/__init__.py
dlint/linters/twisted/inlinecallbacks_yield_statement.py
dlint/linters/twisted/returnvalue_in_inlinecallbacks.py
dlint/linters/twisted/yield_return_statement.py
dlint/redos/__init__.py
dlint/redos/__main__.py
dlint/redos/detect.py
dlint/test/__init__.py
dlint/test/base.py
dlint-0.15.0.dist-info/LICENSE
dlint-0.15.0.dist-info/METADATA
dlint-0.15.0.dist-info/WHEEL
dlint-0.15.0.dist-info/entry_points.txt
dlint-0.15.0.dist-info/top_level.txt
dlint-0.15.0.dist-info/RECORD
