Metadata-Version: 2.1
Name: dlint
Version: 0.15.0
Summary: Dlint is a tool for encouraging best coding practices and helping ensure Python code is secure.
Home-page: https://github.com/dlint-py/dlint
License: BSD-3-Clause
Classifier: Environment :: Console
Classifier: License :: OSI Approved :: BSD License
Classifier: Operating System :: MacOS :: MacOS X
Classifier: Operating System :: Microsoft :: Windows
Classifier: Operating System :: POSIX
Classifier: Programming Language :: Python :: 3.8
Classifier: Programming Language :: Python :: 3.9
Classifier: Programming Language :: Python :: 3.10
Classifier: Programming Language :: Python :: 3.11
Classifier: Programming Language :: Python :: 3.12
Classifier: Topic :: Security
Classifier: Topic :: Software Development :: Quality Assurance
License-File: LICENSE
Requires-Dist: flake8 >=3.6.0
